glyphsLib/__init__.py
glyphsLib/__main__.py
glyphsLib/_version.py
glyphsLib/classes.py
glyphsLib/cli.py
glyphsLib/glyphdata.py
glyphsLib/interpolation.py
glyphsLib/parser.py
glyphsLib/pens.py
glyphsLib/types.py
glyphsLib/util.py
glyphsLib/writer.py
glyphsLib/builder/__init__.py
glyphsLib/builder/anchor_propagation.py
glyphsLib/builder/anchors.py
glyphsLib/builder/annotations.py
glyphsLib/builder/axes.py
glyphsLib/builder/background_image.py
glyphsLib/builder/blue_values.py
glyphsLib/builder/bracket_layers.py
glyphsLib/builder/builders.py
glyphsLib/builder/color_layers.py
glyphsLib/builder/common.py
glyphsLib/builder/components.py
glyphsLib/builder/constants.py
glyphsLib/builder/custom_params.py
glyphsLib/builder/features.py
glyphsLib/builder/filters.py
glyphsLib/builder/font.py
glyphsLib/builder/glyph.py
glyphsLib/builder/groups.py
glyphsLib/builder/guidelines.py
glyphsLib/builder/hints.py
glyphsLib/builder/instances.py
glyphsLib/builder/kerning.py
glyphsLib/builder/layers.py
glyphsLib/builder/masters.py
glyphsLib/builder/names.py
glyphsLib/builder/paths.py
glyphsLib/builder/smart_components.py
glyphsLib/builder/sources.py
glyphsLib/builder/tokens.py
glyphsLib/builder/user_data.py
glyphsLib/builder/transformations/__init__.py
glyphsLib/builder/transformations/align_alternate_layers.py
glyphsLib/builder/transformations/propagate_anchors.py
glyphsLib/data/GlyphData.xml
glyphsLib/data/GlyphData_Ideographs.xml
glyphsLib/data/GlyphData_LICENSE
glyphsLib/data/__init__.py
glyphsLib/featureWriters/__init__.py
glyphsLib/featureWriters/markFeatureWriter.py
glyphsLib/filters/__init__.py
glyphsLib/filters/cornerComponents.py
glyphsLib/filters/eraseOpenCorners.py
glyphslib-6.12.0.dist-info/licenses/LICENSE
glyphslib-6.12.0.dist-info/METADATA
glyphslib-6.12.0.dist-info/WHEEL
glyphslib-6.12.0.dist-info/entry_points.txt
glyphslib-6.12.0.dist-info/top_level.txt
glyphslib-6.12.0.dist-info/RECORD
