Metadata-Version: 2.4
Name: glyphsLib
Version: 6.12.0
Summary: A bridge from Glyphs source files (.glyphs) to UFOs
Home-page: https://github.com/googlefonts/glyphsLib
Author: James Godfrey-Kittle
Author-email: jamesgk@google.com
License: Apache Software License 2.0
Classifier: Development Status :: 4 - Beta
Classifier: Environment :: Console
Classifier: Environment :: Other Environment
Classifier: Intended Audience :: Developers
Classifier: Intended Audience :: End Users/Desktop
Classifier: License :: OSI Approved :: Apache Software License
Classifier: Natural Language :: English
Classifier: Operating System :: OS Independent
Classifier: Programming Language :: Python
Classifier: Programming Language :: Python :: 3
Classifier: Programming Language :: Python :: 3 :: Only
Classifier: Topic :: Multimedia :: Graphics
Classifier: Topic :: Multimedia :: Graphics :: Graphics Conversion
Classifier: Topic :: Multimedia :: Graphics :: Editors :: Vector-Based
Requires-Python: >=3.8
License-File: LICENSE
Requires-Dist: ufoLib2>=0.6.2
Requires-Dist: fonttools[ufo,unicode]>=4.38.0
Requires-Dist: openstep-plist>=0.3.0
Requires-Dist: importlib_resources>=1.3; python_version < "3.9"
Provides-Extra: ufo-normalization
Requires-Dist: ufonormalizer; extra == "ufo-normalization"
Provides-Extra: defcon
Requires-Dist: defcon>=0.6.0; extra == "defcon"
Provides-Extra: colr
Requires-Dist: skia-pathops; extra == "colr"
Dynamic: license-file
